LICENSE.txt
MANIFEST.in
README.rst
setup.cfg
setup.py
defectdojo_api/__init__.py
defectdojo_api/defectdojo.py
defectdojo_api.egg-info/PKG-INFO
defectdojo_api.egg-info/SOURCES.txt
defectdojo_api.egg-info/dependency_links.txt
defectdojo_api.egg-info/requires.txt
defectdojo_api.egg-info/top_level.txt
docs/Makefile
docs/conf.py
docs/defectdojo_api.rst
docs/index.rst
docs/modules.rst