Metadata-Version: 1.1
Name: defectdojo-api
Version: 1.1.3
Summary: An API wrapper for DefectDojo.
Home-page: https://github.com/aaronweaver/defectdojo_api
Author: Aaron Weaver
Author-email: aaron.weaver2@gmail.com
License: MIT
Download-URL: https://github.com/aaronweaver/defectdojo_api/tarball/1.1.3
Keywords: dojo,api,security,software
Platform: UNKNOWN
Classifier: Intended Audience :: Developers
Classifier: Natural Language :: English
Classifier: License :: OSI Approved :: MIT License
Classifier: Topic :: Software Development
Classifier: Topic :: Software Development :: Libraries :: Python Modules
Classifier: Programming Language :: Python :: 2.7
Classifier: Programming Language :: Python :: 3
Classifier: Programming Language :: Python :: 3.2
Classifier: Programming Language :: Python :: 3.3
Classifier: Programming Language :: Python :: 3.4
